{
  "anomalies": [
    {
      "anomaly_index": 232,
      "feature_importances": {
        "Close_1": 35.898,
        "Close_2": 24.034,
        "High_0": 36.05,
        "High_1": 41.808,
        "High_2": 36.089,
        "Low_0": 24.04,
        "Low_1": 23.06,
        "Low_2": 23.724,
        "Open_0": 23.887,
        "Open_1": 42.757,
        "Open_2": 23.805,
        "Volume_0": 247.974,
        "Volume_1": 51.571,
        "Volume_2": 254.401,
        "daily_return_0": 35.373,
        "daily_return_1": 35.864,
        "daily_return_2": 23.879,
        "daily_return_zscore_0": 24.072,
        "daily_return_zscore_1": 23.781,
        "daily_return_zscore_2": 35.53,
        "excess_return_0": 23.768,
        "excess_return_1": 23.761,
        "excess_return_2": 35.543,
        "high_low_range_0": 36.077,
        "high_low_range_1": 23.166,
        "high_low_range_2": 36.085,
        "log_return_0": 42.636,
        "log_return_1": 35.838,
        "log_return_2": 42.648,
        "log_return_zscore_0": 23.829,
        "log_return_zscore_1": 23.479,
        "log_return_zscore_2": 23.654,
        "log_volume_0": 23.97,
        "log_volume_1": 24.06,
        "log_volume_2": 35.939,
        "relative_volume_0": 23.89,
        "relative_volume_1": 43.688,
        "relative_volume_2": 42.552,
        "relative_volume_zscore_0": 23.898,
        "relative_volume_zscore_1": 23.355,
        "relative_volume_zscore_2": 23.366,
        "volume_change_0": 23.566,
        "volume_change_1": 23.349,
        "volume_change_2": 43.633,
        "volume_change_zscore_0": 42.578,
        "volume_change_zscore_1": 23.579,
        "volume_change_zscore_2": 36.058
      }
    },
    {
      "anomaly_index": 233,
      "feature_importances": {
        "Close_1": 23.408,
        "Close_2": 36.093,
        "High_0": 35.908,
        "High_1": 23.879,
        "High_2": 23.788,
        "Low_0": 35.79,
        "Low_1": 23.541,
        "Low_2": 35.596,
        "Open_0": 23.963,
        "Open_1": 23.919,
        "Open_2": 23.099,
        "Volume_0": 50.713,
        "Volume_1": 86.657,
        "Volume_2": 78.026,
        "daily_return_0": 35.892,
        "daily_return_1": 23.969,
        "daily_return_2": 23.775,
        "daily_return_zscore_0": 23.666,
        "daily_return_zscore_1": 24.225,
        "daily_return_zscore_2": 44.972,
        "excess_return_0": 24.099,
        "excess_return_1": 35.808,
        "excess_return_2": 23.771,
        "high_low_range_0": 36.128,
        "high_low_range_1": 35.562,
        "high_low_range_2": 23.539,
        "log_return_0": 35.982,
        "log_return_1": 22.965,
        "log_return_2": 23.541,
        "log_return_zscore_0": 42.935,
        "log_return_zscore_1": 24.226,
        "log_return_zscore_2": 23.781,
        "log_volume_0": 35.72,
        "log_volume_1": 23.706,
        "log_volume_2": 23.533,
        "relative_volume_0": 42.646,
        "relative_volume_1": 24.173,
        "relative_volume_2": 24.078,
        "relative_volume_zscore_0": 24.248,
        "relative_volume_zscore_1": 44.399,
        "relative_volume_zscore_2": 44.241,
        "volume_change_0": 35.393,
        "volume_change_1": 35.736,
        "volume_change_2": 23.749,
        "volume_change_zscore_0": 44.144,
        "volume_change_zscore_1": 42.728,
        "volume_change_zscore_2": 41.8
      }
    },
    {
      "anomaly_index": 234,
      "feature_importances": {
        "Close_1": 23.683,
        "Close_2": 23.491,
        "High_0": 42.406,
        "High_1": 22.471,
        "High_2": 23.007,
        "Low_0": 22.796,
        "Low_1": 23.707,
        "Low_2": 23.309,
        "Open_0": 23.506,
        "Open_1": 23.328,
        "Open_2": 23.871,
        "Volume_0": 109.251,
        "Volume_1": 67.535,
        "Volume_2": 80.801,
        "daily_return_0": 23.563,
        "daily_return_1": 23.505,
        "daily_return_2": 23.866,
        "daily_return_zscore_0": 36.096,
        "daily_return_zscore_1": 43.185,
        "daily_return_zscore_2": 42.269,
        "excess_return_0": 35.691,
        "excess_return_1": 23.766,
        "excess_return_2": 23.599,
        "high_low_range_0": 35.76,
        "high_low_range_1": 23.702,
        "high_low_range_2": 35.763,
        "log_return_0": 35.946,
        "log_return_1": 35.863,
        "log_return_2": 35.403,
        "log_return_zscore_0": 43.267,
        "log_return_zscore_1": 23.938,
        "log_return_zscore_2": 42.483,
        "log_volume_0": 35.878,
        "log_volume_1": 23.879,
        "log_volume_2": 41.63,
        "relative_volume_0": 43.05,
        "relative_volume_1": 23.6,
        "relative_volume_2": 23.502,
        "relative_volume_zscore_0": 35.538,
        "relative_volume_zscore_1": 35.757,
        "relative_volume_zscore_2": 22.791,
        "volume_change_0": 23.925,
        "volume_change_1": 35.561,
        "volume_change_2": 23.646,
        "volume_change_zscore_0": 23.94,
        "volume_change_zscore_1": 35.79,
        "volume_change_zscore_2": 42.231
      }
    },
    {
      "anomaly_index": 427,
      "feature_importances": {
        "Close_1": 23.933,
        "Close_2": 23.996,
        "High_0": 35.937,
        "High_1": 23.667,
        "High_2": 23.326,
        "Low_0": 23.191,
        "Low_1": 23.719,
        "Low_2": 23.992,
        "Open_0": 35.684,
        "Open_1": 35.921,
        "Open_2": 35.797,
        "Volume_0": 66.12,
        "Volume_1": 51.992,
        "Volume_2": 63.575,
        "daily_return_0": 23.604,
        "daily_return_1": 23.131,
        "daily_return_2": 35.407,
        "daily_return_zscore_0": 35.97,
        "daily_return_zscore_1": 41.628,
        "daily_return_zscore_2": 23.014,
        "excess_return_0": 23.486,
        "excess_return_1": 23.072,
        "excess_return_2": 42.297,
        "high_low_range_0": 36.002,
        "high_low_range_1": 35.259,
        "high_low_range_2": 23.773,
        "log_return_0": 23.401,
        "log_return_1": 42.374,
        "log_return_2": 23.638,
        "log_return_zscore_0": 35.522,
        "log_return_zscore_1": 23.514,
        "log_return_zscore_2": 23.375,
        "log_volume_0": 44.52,
        "log_volume_1": 42.57,
        "log_volume_2": 42.747,
        "relative_volume_0": 42.593,
        "relative_volume_1": 23.507,
        "relative_volume_2": 23.987,
        "relative_volume_zscore_0": 23.947,
        "relative_volume_zscore_1": 44.596,
        "relative_volume_zscore_2": 23.85,
        "volume_change_0": 36.022,
        "volume_change_1": 23.897,
        "volume_change_2": 35.874,
        "volume_change_zscore_0": 23.545,
        "volume_change_zscore_1": 35.783,
        "volume_change_zscore_2": 23.819
      }
    },
    {
      "anomaly_index": 428,
      "feature_importances": {
        "Close_1": 35.996,
        "Close_2": 23.814,
        "High_0": 35.759,
        "High_1": 23.145,
        "High_2": 24.113,
        "Low_0": 24.075,
        "Low_1": 42.291,
        "Low_2": 35.907,
        "Open_0": 35.813,
        "Open_1": 36.106,
        "Open_2": 36.069,
        "Volume_0": 47.923,
        "Volume_1": 71.524,
        "Volume_2": 67.119,
        "daily_return_0": 23.285,
        "daily_return_1": 41.937,
        "daily_return_2": 23.452,
        "daily_return_zscore_0": 35.787,
        "daily_return_zscore_1": 24.035,
        "daily_return_zscore_2": 35.606,
        "excess_return_0": 35.852,
        "excess_return_1": 36.0,
        "excess_return_2": 23.32,
        "high_low_range_0": 24.074,
        "high_low_range_1": 36.1,
        "high_low_range_2": 23.175,
        "log_return_0": 36.119,
        "log_return_1": 23.608,
        "log_return_2": 23.576,
        "log_return_zscore_0": 23.706,
        "log_return_zscore_1": 23.279,
        "log_return_zscore_2": 23.264,
        "log_volume_0": 44.882,
        "log_volume_1": 42.749,
        "log_volume_2": 42.56,
        "relative_volume_0": 45.603,
        "relative_volume_1": 23.953,
        "relative_volume_2": 23.502,
        "relative_volume_zscore_0": 23.824,
        "relative_volume_zscore_1": 24.062,
        "relative_volume_zscore_2": 42.739,
        "volume_change_0": 23.907,
        "volume_change_1": 24.07,
        "volume_change_2": 23.866,
        "volume_change_zscore_0": 23.554,
        "volume_change_zscore_1": 46.507,
        "volume_change_zscore_2": 23.683
      }
    },
    {
      "anomaly_index": 429,
      "feature_importances": {
        "Close_1": 23.756,
        "Close_2": 23.161,
        "High_0": 23.76,
        "High_1": 35.547,
        "High_2": 23.482,
        "Low_0": 42.268,
        "Low_1": 35.843,
        "Low_2": 23.581,
        "Open_0": 41.785,
        "Open_1": 35.959,
        "Open_2": 23.76,
        "Volume_0": 118.232,
        "Volume_1": 70.326,
        "Volume_2": 86.821,
        "daily_return_0": 23.503,
        "daily_return_1": 23.438,
        "daily_return_2": 23.52,
        "daily_return_zscore_0": 35.526,
        "daily_return_zscore_1": 23.45,
        "daily_return_zscore_2": 23.839,
        "excess_return_0": 23.723,
        "excess_return_1": 23.298,
        "excess_return_2": 35.346,
        "high_low_range_0": 35.671,
        "high_low_range_1": 23.426,
        "high_low_range_2": 42.287,
        "log_return_0": 23.759,
        "log_return_1": 23.398,
        "log_return_2": 23.704,
        "log_return_zscore_0": 23.764,
        "log_return_zscore_1": 23.859,
        "log_return_zscore_2": 23.372,
        "log_volume_0": 52.133,
        "log_volume_1": 35.373,
        "log_volume_2": 52.204,
        "relative_volume_0": 42.806,
        "relative_volume_1": 23.536,
        "relative_volume_2": 35.795,
        "relative_volume_zscore_0": 35.91,
        "relative_volume_zscore_1": 23.847,
        "relative_volume_zscore_2": 42.664,
        "volume_change_0": 23.636,
        "volume_change_1": 42.303,
        "volume_change_2": 35.708,
        "volume_change_zscore_0": 23.437,
        "volume_change_zscore_1": 35.808,
        "volume_change_zscore_2": 35.688
      }
    },
    {
      "anomaly_index": 440,
      "feature_importances": {
        "Close_1": 46.834,
        "Close_2": 49.119,
        "High_0": 35.236,
        "High_1": 49.124,
        "High_2": 35.649,
        "Low_0": 23.459,
        "Low_1": 49.34,
        "Low_2": 53.779,
        "Open_0": 35.745,
        "Open_1": 35.614,
        "Open_2": 23.07,
        "Volume_0": 42.837,
        "Volume_1": 49.897,
        "Volume_2": 55.206,
        "daily_return_0": 22.728,
        "daily_return_1": 23.635,
        "daily_return_2": 35.708,
        "daily_return_zscore_0": 35.007,
        "daily_return_zscore_1": 23.696,
        "daily_return_zscore_2": 41.463,
        "excess_return_0": 35.752,
        "excess_return_1": 23.5,
        "excess_return_2": 42.22,
        "high_low_range_0": 22.969,
        "high_low_range_1": 35.431,
        "high_low_range_2": 22.95,
        "log_return_0": 23.726,
        "log_return_1": 35.42,
        "log_return_2": 35.553,
        "log_return_zscore_0": 22.728,
        "log_return_zscore_1": 22.75,
        "log_return_zscore_2": 35.6,
        "log_volume_0": 23.811,
        "log_volume_1": 23.204,
        "log_volume_2": 23.482,
        "relative_volume_0": 23.604,
        "relative_volume_1": 42.21,
        "relative_volume_2": 23.797,
        "relative_volume_zscore_0": 23.675,
        "relative_volume_zscore_1": 23.114,
        "relative_volume_zscore_2": 23.762,
        "volume_change_0": 35.662,
        "volume_change_1": 23.446,
        "volume_change_2": 23.72,
        "volume_change_zscore_0": 23.32,
        "volume_change_zscore_1": 23.396,
        "volume_change_zscore_2": 23.338
      }
    },
    {
      "anomaly_index": 441,
      "feature_importances": {
        "Close_1": 35.654,
        "Close_2": 42.395,
        "High_0": 42.431,
        "High_1": 35.678,
        "High_2": 42.358,
        "Low_0": 42.157,
        "Low_1": 42.226,
        "Low_2": 23.89,
        "Open_0": 23.831,
        "Open_1": 23.457,
        "Open_2": 23.963,
        "Volume_0": 58.722,
        "Volume_1": 55.502,
        "Volume_2": 59.03,
        "daily_return_0": 35.481,
        "daily_return_1": 23.769,
        "daily_return_2": 23.369,
        "daily_return_zscore_0": 23.911,
        "daily_return_zscore_1": 35.746,
        "daily_return_zscore_2": 23.597,
        "excess_return_0": 23.752,
        "excess_return_1": 23.894,
        "excess_return_2": 23.638,
        "high_low_range_0": 23.649,
        "high_low_range_1": 23.04,
        "high_low_range_2": 35.544,
        "log_return_0": 24.004,
        "log_return_1": 42.105,
        "log_return_2": 22.77,
        "log_return_zscore_0": 35.834,
        "log_return_zscore_1": 22.855,
        "log_return_zscore_2": 42.208,
        "log_volume_0": 22.911,
        "log_volume_1": 23.521,
        "log_volume_2": 41.726,
        "relative_volume_0": 23.98,
        "relative_volume_1": 23.65,
        "relative_volume_2": 35.948,
        "relative_volume_zscore_0": 35.881,
        "relative_volume_zscore_1": 23.881,
        "relative_volume_zscore_2": 35.756,
        "volume_change_0": 23.857,
        "volume_change_1": 35.573,
        "volume_change_2": 35.957,
        "volume_change_zscore_0": 23.819,
        "volume_change_zscore_1": 35.733,
        "volume_change_zscore_2": 23.785
      }
    },
    {
      "anomaly_index": 442,
      "feature_importances": {
        "Close_1": 23.505,
        "Close_2": 23.328,
        "High_0": 23.358,
        "High_1": 42.179,
        "High_2": 23.678,
        "Low_0": 23.293,
        "Low_1": 35.654,
        "Low_2": 23.565,
        "Open_0": 22.771,
        "Open_1": 23.387,
        "Open_2": 23.611,
        "Volume_0": 51.457,
        "Volume_1": 47.372,
        "Volume_2": 23.675,
        "daily_return_0": 35.361,
        "daily_return_1": 23.287,
        "daily_return_2": 23.628,
        "daily_return_zscore_0": 23.589,
        "daily_return_zscore_1": 23.225,
        "daily_return_zscore_2": 35.582,
        "excess_return_0": 35.748,
        "excess_return_1": 35.315,
        "excess_return_2": 23.58,
        "high_low_range_0": 22.361,
        "high_low_range_1": 42.187,
        "high_low_range_2": 22.995,
        "log_return_0": 35.11,
        "log_return_1": 41.937,
        "log_return_2": 22.73,
        "log_return_zscore_0": 42.224,
        "log_return_zscore_1": 23.648,
        "log_return_zscore_2": 35.402,
        "log_volume_0": 23.346,
        "log_volume_1": 23.456,
        "log_volume_2": 35.534,
        "relative_volume_0": 42.406,
        "relative_volume_1": 35.494,
        "relative_volume_2": 35.672,
        "relative_volume_zscore_0": 23.382,
        "relative_volume_zscore_1": 35.417,
        "relative_volume_zscore_2": 41.629,
        "volume_change_0": 42.208,
        "volume_change_1": 42.01,
        "volume_change_2": 23.6,
        "volume_change_zscore_0": 23.579,
        "volume_change_zscore_1": 35.742,
        "volume_change_zscore_2": 42.305
      }
    },
    {
      "anomaly_index": 443,
      "feature_importances": {
        "Close_1": 23.313,
        "Close_2": 23.534,
        "High_0": 23.643,
        "High_1": 42.1,
        "High_2": 35.519,
        "Low_0": 23.526,
        "Low_1": 23.555,
        "Low_2": 42.32,
        "Open_0": 42.035,
        "Open_1": 23.673,
        "Open_2": 23.335,
        "Volume_0": 51.085,
        "Volume_1": 43.743,
        "Volume_2": 46.965,
        "daily_return_0": 23.367,
        "daily_return_1": 35.679,
        "daily_return_2": 35.701,
        "daily_return_zscore_0": 22.659,
        "daily_return_zscore_1": 42.042,
        "daily_return_zscore_2": 23.486,
        "excess_return_0": 23.154,
        "excess_return_1": 23.647,
        "excess_return_2": 23.43,
        "high_low_range_0": 35.557,
        "high_low_range_1": 35.718,
        "high_low_range_2": 23.653,
        "log_return_0": 35.479,
        "log_return_1": 35.386,
        "log_return_2": 23.2,
        "log_return_zscore_0": 35.667,
        "log_return_zscore_1": 35.202,
        "log_return_zscore_2": 23.463,
        "log_volume_0": 42.194,
        "log_volume_1": 23.385,
        "log_volume_2": 35.481,
        "relative_volume_0": 23.462,
        "relative_volume_1": 23.016,
        "relative_volume_2": 42.075,
        "relative_volume_zscore_0": 35.425,
        "relative_volume_zscore_1": 35.524,
        "relative_volume_zscore_2": 42.327,
        "volume_change_0": 23.593,
        "volume_change_1": 22.443,
        "volume_change_2": 23.432,
        "volume_change_zscore_0": 23.658,
        "volume_change_zscore_1": 22.946,
        "volume_change_zscore_2": 41.549
      }
    },
    {
      "anomaly_index": 444,
      "feature_importances": {
        "Close_1": 23.295,
        "Close_2": 35.629,
        "High_0": 23.723,
        "High_1": 23.628,
        "High_2": 23.164,
        "Low_0": 23.781,
        "Low_1": 41.48,
        "Low_2": 23.832,
        "Open_0": 23.707,
        "Open_1": 23.845,
        "Open_2": 23.38,
        "Volume_0": 57.538,
        "Volume_1": 56.789,
        "Volume_2": 57.392,
        "daily_return_0": 23.898,
        "daily_return_1": 35.909,
        "daily_return_2": 23.462,
        "daily_return_zscore_0": 43.135,
        "daily_return_zscore_1": 35.78,
        "daily_return_zscore_2": 23.733,
        "excess_return_0": 42.323,
        "excess_return_1": 23.915,
        "excess_return_2": 24.005,
        "high_low_range_0": 35.861,
        "high_low_range_1": 35.905,
        "high_low_range_2": 36.177,
        "log_return_0": 23.95,
        "log_return_1": 23.69,
        "log_return_2": 35.81,
        "log_return_zscore_0": 23.668,
        "log_return_zscore_1": 43.936,
        "log_return_zscore_2": 23.969,
        "log_volume_0": 43.344,
        "log_volume_1": 43.677,
        "log_volume_2": 35.748,
        "relative_volume_0": 43.519,
        "relative_volume_1": 23.409,
        "relative_volume_2": 36.149,
        "relative_volume_zscore_0": 23.861,
        "relative_volume_zscore_1": 35.718,
        "relative_volume_zscore_2": 23.778,
        "volume_change_0": 43.636,
        "volume_change_1": 36.153,
        "volume_change_2": 24.038,
        "volume_change_zscore_0": 23.2,
        "volume_change_zscore_1": 23.646,
        "volume_change_zscore_2": 36.012
      }
    },
    {
      "anomaly_index": 448,
      "feature_importances": {
        "Close_1": 42.218,
        "Close_2": 23.458,
        "High_0": 35.398,
        "High_1": 42.031,
        "High_2": 23.561,
        "Low_0": 22.644,
        "Low_1": 41.679,
        "Low_2": 23.041,
        "Open_0": 23.475,
        "Open_1": 35.7,
        "Open_2": 23.758,
        "Volume_0": 57.845,
        "Volume_1": 52.807,
        "Volume_2": 55.317,
        "daily_return_0": 35.791,
        "daily_return_1": 42.037,
        "daily_return_2": 23.173,
        "daily_return_zscore_0": 23.815,
        "daily_return_zscore_1": 23.758,
        "daily_return_zscore_2": 42.616,
        "excess_return_0": 35.716,
        "excess_return_1": 23.795,
        "excess_return_2": 23.114,
        "high_low_range_0": 35.919,
        "high_low_range_1": 35.744,
        "high_low_range_2": 35.859,
        "log_return_0": 35.424,
        "log_return_1": 23.281,
        "log_return_2": 23.39,
        "log_return_zscore_0": 42.337,
        "log_return_zscore_1": 22.947,
        "log_return_zscore_2": 23.103,
        "log_volume_0": 43.087,
        "log_volume_1": 23.63,
        "log_volume_2": 35.5,
        "relative_volume_0": 23.684,
        "relative_volume_1": 23.561,
        "relative_volume_2": 42.528,
        "relative_volume_zscore_0": 23.534,
        "relative_volume_zscore_1": 23.418,
        "relative_volume_zscore_2": 23.48,
        "volume_change_0": 35.872,
        "volume_change_1": 23.851,
        "volume_change_2": 35.817,
        "volume_change_zscore_0": 23.863,
        "volume_change_zscore_1": 23.394,
        "volume_change_zscore_2": 35.866
      }
    },
    {
      "anomaly_index": 450,
      "feature_importances": {
        "Close_1": 36.22,
        "Close_2": 23.487,
        "High_0": 36.229,
        "High_1": 24.032,
        "High_2": 42.441,
        "Low_0": 23.897,
        "Low_1": 23.906,
        "Low_2": 24.034,
        "Open_0": 23.568,
        "Open_1": 24.015,
        "Open_2": 23.661,
        "Volume_0": 83.476,
        "Volume_1": 55.195,
        "Volume_2": 81.046,
        "daily_return_0": 23.58,
        "daily_return_1": 35.965,
        "daily_return_2": 35.82,
        "daily_return_zscore_0": 23.43,
        "daily_return_zscore_1": 23.536,
        "daily_return_zscore_2": 23.733,
        "excess_return_0": 23.626,
        "excess_return_1": 23.929,
        "excess_return_2": 23.609,
        "high_low_range_0": 35.971,
        "high_low_range_1": 42.532,
        "high_low_range_2": 23.883,
        "log_return_0": 23.938,
        "log_return_1": 35.516,
        "log_return_2": 23.44,
        "log_return_zscore_0": 42.605,
        "log_return_zscore_1": 23.749,
        "log_return_zscore_2": 42.609,
        "log_volume_0": 42.634,
        "log_volume_1": 35.721,
        "log_volume_2": 42.434,
        "relative_volume_0": 23.534,
        "relative_volume_1": 23.828,
        "relative_volume_2": 23.942,
        "relative_volume_zscore_0": 41.929,
        "relative_volume_zscore_1": 36.098,
        "relative_volume_zscore_2": 24.022,
        "volume_change_0": 35.918,
        "volume_change_1": 36.267,
        "volume_change_2": 23.905,
        "volume_change_zscore_0": 42.87,
        "volume_change_zscore_1": 35.575,
        "volume_change_zscore_2": 35.751
      }
    },
    {
      "anomaly_index": 458,
      "feature_importances": {
        "Close_1": 23.745,
        "Close_2": 23.982,
        "High_0": 23.007,
        "High_1": 23.532,
        "High_2": 23.6,
        "Low_0": 35.586,
        "Low_1": 23.325,
        "Low_2": 23.945,
        "Open_0": 35.764,
        "Open_1": 24.097,
        "Open_2": 24.113,
        "Volume_0": 66.649,
        "Volume_1": 57.541,
        "Volume_2": 81.794,
        "daily_return_0": 23.544,
        "daily_return_1": 23.617,
        "daily_return_2": 35.732,
        "daily_return_zscore_0": 41.881,
        "daily_return_zscore_1": 24.125,
        "daily_return_zscore_2": 23.638,
        "excess_return_0": 24.12,
        "excess_return_1": 23.768,
        "excess_return_2": 36.037,
        "high_low_range_0": 23.963,
        "high_low_range_1": 24.058,
        "high_low_range_2": 24.079,
        "log_return_0": 35.746,
        "log_return_1": 23.852,
        "log_return_2": 42.413,
        "log_return_zscore_0": 36.003,
        "log_return_zscore_1": 36.114,
        "log_return_zscore_2": 43.875,
        "log_volume_0": 43.115,
        "log_volume_1": 45.326,
        "log_volume_2": 23.778,
        "relative_volume_0": 23.497,
        "relative_volume_1": 35.843,
        "relative_volume_2": 43.199,
        "relative_volume_zscore_0": 43.696,
        "relative_volume_zscore_1": 36.057,
        "relative_volume_zscore_2": 23.614,
        "volume_change_0": 23.83,
        "volume_change_1": 35.726,
        "volume_change_2": 45.599,
        "volume_change_zscore_0": 35.699,
        "volume_change_zscore_1": 22.54,
        "volume_change_zscore_2": 35.556
      }
    },
    {
      "anomaly_index": 459,
      "feature_importances": {
        "Close_1": 42.186,
        "Close_2": 42.706,
        "High_0": 24.052,
        "High_1": 24.034,
        "High_2": 36.054,
        "Low_0": 42.555,
        "Low_1": 35.901,
        "Low_2": 35.843,
        "Open_0": 24.016,
        "Open_1": 35.833,
        "Open_2": 23.671,
        "Volume_0": 66.188,
        "Volume_1": 75.643,
        "Volume_2": 51.35,
        "daily_return_0": 36.051,
        "daily_return_1": 23.447,
        "daily_return_2": 35.798,
        "daily_return_zscore_0": 23.502,
        "daily_return_zscore_1": 24.135,
        "daily_return_zscore_2": 42.196,
        "excess_return_0": 23.938,
        "excess_return_1": 24.158,
        "excess_return_2": 23.659,
        "high_low_range_0": 23.033,
        "high_low_range_1": 36.059,
        "high_low_range_2": 35.925,
        "log_return_0": 22.698,
        "log_return_1": 36.04,
        "log_return_2": 36.012,
        "log_return_zscore_0": 41.726,
        "log_return_zscore_1": 42.287,
        "log_return_zscore_2": 23.746,
        "log_volume_0": 42.324,
        "log_volume_1": 24.162,
        "log_volume_2": 35.691,
        "relative_volume_0": 23.848,
        "relative_volume_1": 23.608,
        "relative_volume_2": 23.985,
        "relative_volume_zscore_0": 23.594,
        "relative_volume_zscore_1": 23.91,
        "relative_volume_zscore_2": 42.434,
        "volume_change_0": 24.143,
        "volume_change_1": 23.776,
        "volume_change_2": 23.731,
        "volume_change_zscore_0": 23.892,
        "volume_change_zscore_1": 36.06,
        "volume_change_zscore_2": 23.649
      }
    },
    {
      "anomaly_index": 460,
      "feature_importances": {
        "Close_1": 23.884,
        "Close_2": 35.784,
        "High_0": 41.901,
        "High_1": 24.047,
        "High_2": 35.753,
        "Low_0": 35.946,
        "Low_1": 23.04,
        "Low_2": 24.029,
        "Open_0": 23.669,
        "Open_1": 23.945,
        "Open_2": 23.62,
        "Volume_0": 76.078,
        "Volume_1": 49.189,
        "Volume_2": 68.226,
        "daily_return_0": 23.245,
        "daily_return_1": 36.112,
        "daily_return_2": 35.929,
        "daily_return_zscore_0": 43.286,
        "daily_return_zscore_1": 36.042,
        "daily_return_zscore_2": 23.216,
        "excess_return_0": 35.737,
        "excess_return_1": 23.701,
        "excess_return_2": 23.883,
        "high_low_range_0": 22.946,
        "high_low_range_1": 42.379,
        "high_low_range_2": 23.409,
        "log_return_0": 24.177,
        "log_return_1": 23.952,
        "log_return_2": 23.797,
        "log_return_zscore_0": 43.945,
        "log_return_zscore_1": 23.376,
        "log_return_zscore_2": 24.058,
        "log_volume_0": 24.036,
        "log_volume_1": 23.88,
        "log_volume_2": 35.667,
        "relative_volume_0": 42.748,
        "relative_volume_1": 42.363,
        "relative_volume_2": 24.172,
        "relative_volume_zscore_0": 44.952,
        "relative_volume_zscore_1": 35.621,
        "relative_volume_zscore_2": 35.574,
        "volume_change_0": 36.019,
        "volume_change_1": 36.034,
        "volume_change_2": 24.067,
        "volume_change_zscore_0": 23.788,
        "volume_change_zscore_1": 42.427,
        "volume_change_zscore_2": 23.78
      }
    },
    {
      "anomaly_index": 464,
      "feature_importances": {
        "Close_1": 23.55,
        "Close_2": 36.21,
        "High_0": 35.829,
        "High_1": 42.565,
        "High_2": 23.519,
        "Low_0": 42.737,
        "Low_1": 23.452,
        "Low_2": 41.864,
        "Open_0": 42.866,
        "Open_1": 23.414,
        "Open_2": 36.131,
        "Volume_0": 208.924,
        "Volume_1": 64.299,
        "Volume_2": 223.279,
        "daily_return_0": 23.47,
        "daily_return_1": 24.015,
        "daily_return_2": 23.977,
        "daily_return_zscore_0": 23.647,
        "daily_return_zscore_1": 35.503,
        "daily_return_zscore_2": 23.572,
        "excess_return_0": 35.93,
        "excess_return_1": 23.676,
        "excess_return_2": 24.074,
        "high_low_range_0": 42.581,
        "high_low_range_1": 23.733,
        "high_low_range_2": 42.543,
        "log_return_0": 36.045,
        "log_return_1": 35.879,
        "log_return_2": 24.08,
        "log_return_zscore_0": 36.26,
        "log_return_zscore_1": 23.754,
        "log_return_zscore_2": 42.861,
        "log_volume_0": 23.887,
        "log_volume_1": 23.086,
        "log_volume_2": 36.256,
        "relative_volume_0": 23.721,
        "relative_volume_1": 23.904,
        "relative_volume_2": 42.687,
        "relative_volume_zscore_0": 35.951,
        "relative_volume_zscore_1": 23.814,
        "relative_volume_zscore_2": 23.342,
        "volume_change_0": 23.667,
        "volume_change_1": 35.956,
        "volume_change_2": 24.13,
        "volume_change_zscore_0": 23.726,
        "volume_change_zscore_1": 23.828,
        "volume_change_zscore_2": 36.062
      }
    },
    {
      "anomaly_index": 469,
      "feature_importances": {
        "Close_1": 35.626,
        "Close_2": 23.44,
        "High_0": 35.462,
        "High_1": 23.664,
        "High_2": 35.803,
        "Low_0": 22.791,
        "Low_1": 23.472,
        "Low_2": 23.682,
        "Open_0": 23.391,
        "Open_1": 23.522,
        "Open_2": 35.147,
        "Volume_0": 44.54,
        "Volume_1": 45.296,
        "Volume_2": 52.248,
        "daily_return_0": 23.595,
        "daily_return_1": 35.543,
        "daily_return_2": 23.438,
        "daily_return_zscore_0": 35.358,
        "daily_return_zscore_1": 42.413,
        "daily_return_zscore_2": 44.528,
        "excess_return_0": 23.69,
        "excess_return_1": 35.94,
        "excess_return_2": 23.45,
        "high_low_range_0": 23.388,
        "high_low_range_1": 35.764,
        "high_low_range_2": 35.711,
        "log_return_0": 23.518,
        "log_return_1": 23.129,
        "log_return_2": 22.901,
        "log_return_zscore_0": 35.386,
        "log_return_zscore_1": 35.757,
        "log_return_zscore_2": 23.06,
        "log_volume_0": 47.638,
        "log_volume_1": 23.462,
        "log_volume_2": 42.681,
        "relative_volume_0": 23.275,
        "relative_volume_1": 23.346,
        "relative_volume_2": 23.609,
        "relative_volume_zscore_0": 47.366,
        "relative_volume_zscore_1": 23.589,
        "relative_volume_zscore_2": 23.566,
        "volume_change_0": 23.135,
        "volume_change_1": 41.72,
        "volume_change_2": 35.865,
        "volume_change_zscore_0": 23.195,
        "volume_change_zscore_1": 42.14,
        "volume_change_zscore_2": 53.183
      }
    },
    {
      "anomaly_index": 470,
      "feature_importances": {
        "Close_1": 35.923,
        "Close_2": 42.283,
        "High_0": 23.468,
        "High_1": 23.876,
        "High_2": 23.034,
        "Low_0": 23.527,
        "Low_1": 35.819,
        "Low_2": 23.54,
        "Open_0": 23.24,
        "Open_1": 23.421,
        "Open_2": 35.694,
        "Volume_0": 55.062,
        "Volume_1": 57.715,
        "Volume_2": 46.597,
        "daily_return_0": 35.501,
        "daily_return_1": 23.906,
        "daily_return_2": 35.303,
        "daily_return_zscore_0": 35.805,
        "daily_return_zscore_1": 23.079,
        "daily_return_zscore_2": 41.736,
        "excess_return_0": 23.369,
        "excess_return_1": 23.638,
        "excess_return_2": 23.14,
        "high_low_range_0": 42.551,
        "high_low_range_1": 23.884,
        "high_low_range_2": 23.331,
        "log_return_0": 23.547,
        "log_return_1": 23.832,
        "log_return_2": 23.333,
        "log_return_zscore_0": 23.262,
        "log_return_zscore_1": 23.936,
        "log_return_zscore_2": 23.751,
        "log_volume_0": 44.113,
        "log_volume_1": 42.352,
        "log_volume_2": 23.167,
        "relative_volume_0": 23.405,
        "relative_volume_1": 35.646,
        "relative_volume_2": 23.608,
        "relative_volume_zscore_0": 35.86,
        "relative_volume_zscore_1": 23.294,
        "relative_volume_zscore_2": 35.137,
        "volume_change_0": 42.365,
        "volume_change_1": 43.853,
        "volume_change_2": 42.596,
        "volume_change_zscore_0": 35.865,
        "volume_change_zscore_1": 35.909,
        "volume_change_zscore_2": 35.814
      }
    },
    {
      "anomaly_index": 471,
      "feature_importances": {
        "Close_1": 23.001,
        "Close_2": 23.054,
        "High_0": 35.547,
        "High_1": 22.768,
        "High_2": 22.654,
        "Low_0": 23.649,
        "Low_1": 42.361,
        "Low_2": 23.597,
        "Open_0": 22.99,
        "Open_1": 23.439,
        "Open_2": 23.679,
        "Volume_0": 53.019,
        "Volume_1": 42.53,
        "Volume_2": 49.176,
        "daily_return_0": 23.194,
        "daily_return_1": 23.323,
        "daily_return_2": 23.119,
        "daily_return_zscore_0": 23.223,
        "daily_return_zscore_1": 42.384,
        "daily_return_zscore_2": 23.431,
        "excess_return_0": 35.477,
        "excess_return_1": 35.52,
        "excess_return_2": 23.346,
        "high_low_range_0": 41.612,
        "high_low_range_1": 23.588,
        "high_low_range_2": 35.034,
        "log_return_0": 23.433,
        "log_return_1": 35.921,
        "log_return_2": 35.489,
        "log_return_zscore_0": 43.024,
        "log_return_zscore_1": 35.383,
        "log_return_zscore_2": 23.512,
        "log_volume_0": 35.908,
        "log_volume_1": 35.706,
        "log_volume_2": 42.844,
        "relative_volume_0": 23.804,
        "relative_volume_1": 22.907,
        "relative_volume_2": 35.885,
        "relative_volume_zscore_0": 35.538,
        "relative_volume_zscore_1": 35.76,
        "relative_volume_zscore_2": 42.67,
        "volume_change_0": 23.249,
        "volume_change_1": 23.689,
        "volume_change_2": 23.389,
        "volume_change_zscore_0": 42.225,
        "volume_change_zscore_1": 42.103,
        "volume_change_zscore_2": 23.771
      }
    },
    {
      "anomaly_index": 472,
      "feature_importances": {
        "Close_1": 23.88,
        "Close_2": 35.523,
        "High_0": 23.315,
        "High_1": 23.468,
        "High_2": 41.656,
        "Low_0": 35.475,
        "Low_1": 36.061,
        "Low_2": 23.827,
        "Open_0": 23.779,
        "Open_1": 23.213,
        "Open_2": 23.489,
        "Volume_0": 46.554,
        "Volume_1": 50.431,
        "Volume_2": 50.955,
        "daily_return_0": 23.438,
        "daily_return_1": 23.738,
        "daily_return_2": 35.85,
        "daily_return_zscore_0": 23.235,
        "daily_return_zscore_1": 35.982,
        "daily_return_zscore_2": 35.856,
        "excess_return_0": 23.906,
        "excess_return_1": 23.893,
        "excess_return_2": 23.757,
        "high_low_range_0": 35.635,
        "high_low_range_1": 23.443,
        "high_low_range_2": 23.726,
        "log_return_0": 23.351,
        "log_return_1": 23.706,
        "log_return_2": 35.977,
        "log_return_zscore_0": 42.541,
        "log_return_zscore_1": 35.539,
        "log_return_zscore_2": 23.643,
        "log_volume_0": 45.33,
        "log_volume_1": 23.906,
        "log_volume_2": 23.737,
        "relative_volume_0": 42.118,
        "relative_volume_1": 35.662,
        "relative_volume_2": 23.752,
        "relative_volume_zscore_0": 23.806,
        "relative_volume_zscore_1": 44.388,
        "relative_volume_zscore_2": 23.667,
        "volume_change_0": 23.995,
        "volume_change_1": 42.46,
        "volume_change_2": 35.992,
        "volume_change_zscore_0": 42.509,
        "volume_change_zscore_1": 42.826,
        "volume_change_zscore_2": 35.988
      }
    },
    {
      "anomaly_index": 473,
      "feature_importances": {
        "Close_1": 23.7,
        "Close_2": 23.508,
        "High_0": 23.169,
        "High_1": 35.671,
        "High_2": 42.009,
        "Low_0": 23.491,
        "Low_1": 35.773,
        "Low_2": 23.577,
        "Open_0": 35.577,
        "Open_1": 22.743,
        "Open_2": 23.642,
        "Volume_0": 58.575,
        "Volume_1": 45.664,
        "Volume_2": 53.911,
        "daily_return_0": 23.825,
        "daily_return_1": 35.681,
        "daily_return_2": 23.906,
        "daily_return_zscore_0": 35.454,
        "daily_return_zscore_1": 35.335,
        "daily_return_zscore_2": 23.428,
        "excess_return_0": 23.695,
        "excess_return_1": 23.895,
        "excess_return_2": 41.366,
        "high_low_range_0": 23.68,
        "high_low_range_1": 35.195,
        "high_low_range_2": 35.581,
        "log_return_0": 23.583,
        "log_return_1": 22.797,
        "log_return_2": 23.228,
        "log_return_zscore_0": 43.027,
        "log_return_zscore_1": 23.872,
        "log_return_zscore_2": 35.478,
        "log_volume_0": 42.941,
        "log_volume_1": 42.6,
        "log_volume_2": 35.699,
        "relative_volume_0": 23.629,
        "relative_volume_1": 23.294,
        "relative_volume_2": 22.934,
        "relative_volume_zscore_0": 35.654,
        "relative_volume_zscore_1": 23.614,
        "relative_volume_zscore_2": 23.757,
        "volume_change_0": 35.475,
        "volume_change_1": 23.337,
        "volume_change_2": 42.261,
        "volume_change_zscore_0": 22.913,
        "volume_change_zscore_1": 42.112,
        "volume_change_zscore_2": 42.169
      }
    },
    {
      "anomaly_index": 474,
      "feature_importances": {
        "Close_1": 23.545,
        "Close_2": 35.481,
        "High_0": 23.505,
        "High_1": 35.596,
        "High_2": 23.045,
        "Low_0": 35.565,
        "Low_1": 23.716,
        "Low_2": 22.857,
        "Open_0": 23.614,
        "Open_1": 35.899,
        "Open_2": 23.278,
        "Volume_0": 48.567,
        "Volume_1": 46.295,
        "Volume_2": 49.707,
        "daily_return_0": 23.105,
        "daily_return_1": 35.691,
        "daily_return_2": 23.745,
        "daily_return_zscore_0": 23.594,
        "daily_return_zscore_1": 42.567,
        "daily_return_zscore_2": 46.82,
        "excess_return_0": 41.595,
        "excess_return_1": 23.395,
        "excess_return_2": 35.767,
        "high_low_range_0": 23.383,
        "high_low_range_1": 42.124,
        "high_low_range_2": 23.333,
        "log_return_0": 23.66,
        "log_return_1": 35.581,
        "log_return_2": 35.455,
        "log_return_zscore_0": 42.871,
        "log_return_zscore_1": 23.364,
        "log_return_zscore_2": 49.506,
        "log_volume_0": 23.821,
        "log_volume_1": 23.216,
        "log_volume_2": 54.461,
        "relative_volume_0": 23.401,
        "relative_volume_1": 23.777,
        "relative_volume_2": 35.143,
        "relative_volume_zscore_0": 23.216,
        "relative_volume_zscore_1": 23.876,
        "relative_volume_zscore_2": 35.861,
        "volume_change_0": 23.745,
        "volume_change_1": 23.521,
        "volume_change_2": 35.781,
        "volume_change_zscore_0": 23.697,
        "volume_change_zscore_1": 35.625,
        "volume_change_zscore_2": 42.117
      }
    },
    {
      "anomaly_index": 475,
      "feature_importances": {
        "Close_1": 23.471,
        "Close_2": 23.297,
        "High_0": 35.498,
        "High_1": 23.634,
        "High_2": 35.776,
        "Low_0": 23.657,
        "Low_1": 41.915,
        "Low_2": 42.141,
        "Open_0": 23.347,
        "Open_1": 23.556,
        "Open_2": 22.756,
        "Volume_0": 52.237,
        "Volume_1": 44.639,
        "Volume_2": 54.729,
        "daily_return_0": 42.31,
        "daily_return_1": 23.604,
        "daily_return_2": 23.609,
        "daily_return_zscore_0": 23.551,
        "daily_return_zscore_1": 35.807,
        "daily_return_zscore_2": 35.693,
        "excess_return_0": 23.384,
        "excess_return_1": 22.439,
        "excess_return_2": 42.239,
        "high_low_range_0": 23.269,
        "high_low_range_1": 35.557,
        "high_low_range_2": 23.337,
        "log_return_0": 23.677,
        "log_return_1": 35.586,
        "log_return_2": 22.993,
        "log_return_zscore_0": 41.6,
        "log_return_zscore_1": 43.019,
        "log_return_zscore_2": 23.159,
        "log_volume_0": 42.967,
        "log_volume_1": 42.487,
        "log_volume_2": 23.676,
        "relative_volume_0": 23.17,
        "relative_volume_1": 23.273,
        "relative_volume_2": 23.397,
        "relative_volume_zscore_0": 35.728,
        "relative_volume_zscore_1": 23.455,
        "relative_volume_zscore_2": 35.77,
        "volume_change_0": 22.801,
        "volume_change_1": 35.699,
        "volume_change_2": 35.66,
        "volume_change_zscore_0": 23.391,
        "volume_change_zscore_1": 35.514,
        "volume_change_zscore_2": 35.459
      }
    },
    {
      "anomaly_index": 476,
      "feature_importances": {
        "Close_1": 36.103,
        "Close_2": 36.081,
        "High_0": 23.557,
        "High_1": 36.122,
        "High_2": 23.64,
        "Low_0": 23.638,
        "Low_1": 23.195,
        "Low_2": 23.876,
        "Open_0": 23.787,
        "Open_1": 35.978,
        "Open_2": 36.133,
        "Volume_0": 49.333,
        "Volume_1": 51.736,
        "Volume_2": 51.473,
        "daily_return_0": 41.883,
        "daily_return_1": 23.326,
        "daily_return_2": 23.996,
        "daily_return_zscore_0": 22.601,
        "daily_return_zscore_1": 36.078,
        "daily_return_zscore_2": 44.166,
        "excess_return_0": 23.263,
        "excess_return_1": 23.597,
        "excess_return_2": 23.408,
        "high_low_range_0": 23.84,
        "high_low_range_1": 24.018,
        "high_low_range_2": 22.869,
        "log_return_0": 35.858,
        "log_return_1": 23.47,
        "log_return_2": 23.475,
        "log_return_zscore_0": 43.262,
        "log_return_zscore_1": 23.722,
        "log_return_zscore_2": 44.527,
        "log_volume_0": 46.316,
        "log_volume_1": 43.31,
        "log_volume_2": 36.028,
        "relative_volume_0": 36.054,
        "relative_volume_1": 23.0,
        "relative_volume_2": 23.822,
        "relative_volume_zscore_0": 35.806,
        "relative_volume_zscore_1": 23.467,
        "relative_volume_zscore_2": 43.222,
        "volume_change_0": 23.433,
        "volume_change_1": 23.31,
        "volume_change_2": 36.169,
        "volume_change_zscore_0": 24.011,
        "volume_change_zscore_1": 44.099,
        "volume_change_zscore_2": 35.942
      }
    },
    {
      "anomaly_index": 477,
      "feature_importances": {
        "Close_1": 23.435,
        "Close_2": 23.583,
        "High_0": 35.362,
        "High_1": 22.935,
        "High_2": 23.672,
        "Low_0": 23.636,
        "Low_1": 42.301,
        "Low_2": 42.168,
        "Open_0": 35.418,
        "Open_1": 35.693,
        "Open_2": 42.402,
        "Volume_0": 55.056,
        "Volume_1": 47.92,
        "Volume_2": 50.364,
        "daily_return_0": 23.366,
        "daily_return_1": 35.796,
        "daily_return_2": 23.452,
        "daily_return_zscore_0": 42.174,
        "daily_return_zscore_1": 23.427,
        "daily_return_zscore_2": 23.538,
        "excess_return_0": 22.92,
        "excess_return_1": 35.54,
        "excess_return_2": 35.355,
        "high_low_range_0": 35.63,
        "high_low_range_1": 41.543,
        "high_low_range_2": 35.482,
        "log_return_0": 23.299,
        "log_return_1": 23.593,
        "log_return_2": 23.546,
        "log_return_zscore_0": 23.514,
        "log_return_zscore_1": 46.661,
        "log_return_zscore_2": 23.459,
        "log_volume_0": 46.551,
        "log_volume_1": 35.801,
        "log_volume_2": 35.417,
        "relative_volume_0": 41.957,
        "relative_volume_1": 23.47,
        "relative_volume_2": 23.305,
        "relative_volume_zscore_0": 35.804,
        "relative_volume_zscore_1": 23.595,
        "relative_volume_zscore_2": 23.493,
        "volume_change_0": 23.573,
        "volume_change_1": 23.068,
        "volume_change_2": 23.631,
        "volume_change_zscore_0": 35.424,
        "volume_change_zscore_1": 23.386,
        "volume_change_zscore_2": 23.288
      }
    },
    {
      "anomaly_index": 483,
      "feature_importances": {
        "Close_1": 42.428,
        "Close_2": 23.839,
        "High_0": 36.153,
        "High_1": 23.753,
        "High_2": 35.828,
        "Low_0": 24.014,
        "Low_1": 36.166,
        "Low_2": 24.152,
        "Open_0": 23.194,
        "Open_1": 23.373,
        "Open_2": 35.991,
        "Volume_0": 72.135,
        "Volume_1": 49.968,
        "Volume_2": 72.642,
        "daily_return_0": 23.696,
        "daily_return_1": 23.428,
        "daily_return_2": 23.3,
        "daily_return_zscore_0": 23.227,
        "daily_return_zscore_1": 45.362,
        "daily_return_zscore_2": 23.503,
        "excess_return_0": 35.914,
        "excess_return_1": 23.604,
        "excess_return_2": 35.892,
        "high_low_range_0": 35.829,
        "high_low_range_1": 23.687,
        "high_low_range_2": 23.375,
        "log_return_0": 24.182,
        "log_return_1": 35.741,
        "log_return_2": 23.655,
        "log_return_zscore_0": 41.933,
        "log_return_zscore_1": 35.994,
        "log_return_zscore_2": 43.62,
        "log_volume_0": 52.448,
        "log_volume_1": 23.776,
        "log_volume_2": 23.938,
        "relative_volume_0": 23.856,
        "relative_volume_1": 42.476,
        "relative_volume_2": 23.425,
        "relative_volume_zscore_0": 23.255,
        "relative_volume_zscore_1": 36.218,
        "relative_volume_zscore_2": 46.319,
        "volume_change_0": 35.828,
        "volume_change_1": 23.848,
        "volume_change_2": 24.07,
        "volume_change_zscore_0": 36.08,
        "volume_change_zscore_1": 51.654,
        "volume_change_zscore_2": 23.972
      }
    },
    {
      "anomaly_index": 484,
      "feature_importances": {
        "Close_1": 35.736,
        "Close_2": 23.596,
        "High_0": 36.175,
        "High_1": 35.71,
        "High_2": 23.796,
        "Low_0": 23.18,
        "Low_1": 35.593,
        "Low_2": 22.83,
        "Open_0": 35.648,
        "Open_1": 36.014,
        "Open_2": 23.987,
        "Volume_0": 49.765,
        "Volume_1": 52.122,
        "Volume_2": 52.585,
        "daily_return_0": 23.794,
        "daily_return_1": 35.742,
        "daily_return_2": 23.515,
        "daily_return_zscore_0": 44.895,
        "daily_return_zscore_1": 47.204,
        "daily_return_zscore_2": 42.363,
        "excess_return_0": 23.42,
        "excess_return_1": 23.263,
        "excess_return_2": 22.918,
        "high_low_range_0": 35.881,
        "high_low_range_1": 23.612,
        "high_low_range_2": 23.642,
        "log_return_0": 23.901,
        "log_return_1": 23.595,
        "log_return_2": 23.612,
        "log_return_zscore_0": 47.788,
        "log_return_zscore_1": 47.103,
        "log_return_zscore_2": 36.082,
        "log_volume_0": 53.704,
        "log_volume_1": 23.582,
        "log_volume_2": 35.956,
        "relative_volume_0": 23.624,
        "relative_volume_1": 23.967,
        "relative_volume_2": 23.885,
        "relative_volume_zscore_0": 35.865,
        "relative_volume_zscore_1": 51.889,
        "relative_volume_zscore_2": 45.902,
        "volume_change_0": 36.053,
        "volume_change_1": 23.451,
        "volume_change_2": 23.676,
        "volume_change_zscore_0": 23.983,
        "volume_change_zscore_1": 23.831,
        "volume_change_zscore_2": 23.535
      }
    },
    {
      "anomaly_index": 485,
      "feature_importances": {
        "Close_1": 23.679,
        "Close_2": 42.47,
        "High_0": 35.898,
        "High_1": 24.08,
        "High_2": 22.729,
        "Low_0": 23.544,
        "Low_1": 23.616,
        "Low_2": 35.985,
        "Open_0": 24.141,
        "Open_1": 23.147,
        "Open_2": 24.044,
        "Volume_0": 67.925,
        "Volume_1": 53.974,
        "Volume_2": 64.546,
        "daily_return_0": 24.144,
        "daily_return_1": 23.88,
        "daily_return_2": 23.841,
        "daily_return_zscore_0": 35.717,
        "daily_return_zscore_1": 35.972,
        "daily_return_zscore_2": 23.712,
        "excess_return_0": 41.906,
        "excess_return_1": 23.777,
        "excess_return_2": 35.921,
        "high_low_range_0": 35.824,
        "high_low_range_1": 42.7,
        "high_low_range_2": 23.734,
        "log_return_0": 36.007,
        "log_return_1": 23.436,
        "log_return_2": 23.65,
        "log_return_zscore_0": 42.923,
        "log_return_zscore_1": 23.802,
        "log_return_zscore_2": 35.647,
        "log_volume_0": 24.235,
        "log_volume_1": 42.958,
        "log_volume_2": 36.11,
        "relative_volume_0": 23.816,
        "relative_volume_1": 42.549,
        "relative_volume_2": 23.337,
        "relative_volume_zscore_0": 24.025,
        "relative_volume_zscore_1": 23.88,
        "relative_volume_zscore_2": 35.901,
        "volume_change_0": 42.548,
        "volume_change_1": 35.723,
        "volume_change_2": 42.447,
        "volume_change_zscore_0": 23.449,
        "volume_change_zscore_1": 35.959,
        "volume_change_zscore_2": 23.489
      }
    },
    {
      "anomaly_index": 486,
      "feature_importances": {
        "Close_1": 24.14,
        "Close_2": 23.096,
        "High_0": 35.734,
        "High_1": 23.709,
        "High_2": 24.242,
        "Low_0": 41.896,
        "Low_1": 24.249,
        "Low_2": 24.076,
        "Open_0": 42.507,
        "Open_1": 23.653,
        "Open_2": 23.778,
        "Volume_0": 92.483,
        "Volume_1": 60.221,
        "Volume_2": 99.045,
        "daily_return_0": 24.119,
        "daily_return_1": 35.661,
        "daily_return_2": 23.254,
        "daily_return_zscore_0": 36.174,
        "daily_return_zscore_1": 23.98,
        "daily_return_zscore_2": 36.039,
        "excess_return_0": 35.97,
        "excess_return_1": 23.89,
        "excess_return_2": 36.096,
        "high_low_range_0": 23.445,
        "high_low_range_1": 23.676,
        "high_low_range_2": 36.049,
        "log_return_0": 35.725,
        "log_return_1": 23.364,
        "log_return_2": 23.747,
        "log_return_zscore_0": 23.638,
        "log_return_zscore_1": 24.0,
        "log_return_zscore_2": 24.217,
        "log_volume_0": 23.135,
        "log_volume_1": 42.334,
        "log_volume_2": 42.308,
        "relative_volume_0": 42.683,
        "relative_volume_1": 35.802,
        "relative_volume_2": 23.967,
        "relative_volume_zscore_0": 42.641,
        "relative_volume_zscore_1": 23.429,
        "relative_volume_zscore_2": 35.958,
        "volume_change_0": 24.106,
        "volume_change_1": 36.116,
        "volume_change_2": 35.985,
        "volume_change_zscore_0": 23.943,
        "volume_change_zscore_1": 42.506,
        "volume_change_zscore_2": 42.557
      }
    },
    {
      "anomaly_index": 494,
      "feature_importances": {
        "Close_1": 23.562,
        "Close_2": 23.635,
        "High_0": 35.591,
        "High_1": 42.376,
        "High_2": 23.697,
        "Low_0": 23.12,
        "Low_1": 35.695,
        "Low_2": 22.993,
        "Open_0": 42.16,
        "Open_1": 35.804,
        "Open_2": 23.518,
        "Volume_0": 44.003,
        "Volume_1": 53.732,
        "Volume_2": 59.908,
        "daily_return_0": 35.752,
        "daily_return_1": 23.631,
        "daily_return_2": 35.757,
        "daily_return_zscore_0": 23.254,
        "daily_return_zscore_1": 35.576,
        "daily_return_zscore_2": 42.13,
        "excess_return_0": 23.139,
        "excess_return_1": 35.678,
        "excess_return_2": 23.38,
        "high_low_range_0": 42.215,
        "high_low_range_1": 23.095,
        "high_low_range_2": 23.244,
        "log_return_0": 23.401,
        "log_return_1": 42.337,
        "log_return_2": 23.192,
        "log_return_zscore_0": 23.276,
        "log_return_zscore_1": 23.657,
        "log_return_zscore_2": 23.485,
        "log_volume_0": 23.658,
        "log_volume_1": 23.082,
        "log_volume_2": 35.748,
        "relative_volume_0": 42.227,
        "relative_volume_1": 41.439,
        "relative_volume_2": 23.315,
        "relative_volume_zscore_0": 23.707,
        "relative_volume_zscore_1": 22.922,
        "relative_volume_zscore_2": 35.55,
        "volume_change_0": 35.584,
        "volume_change_1": 23.19,
        "volume_change_2": 35.484,
        "volume_change_zscore_0": 42.269,
        "volume_change_zscore_1": 35.497,
        "volume_change_zscore_2": 23.226
      }
    },
    {
      "anomaly_index": 495,
      "feature_importances": {
        "Close_1": 23.756,
        "Close_2": 23.128,
        "High_0": 35.287,
        "High_1": 23.606,
        "High_2": 23.761,
        "Low_0": 35.78,
        "Low_1": 35.511,
        "Low_2": 23.533,
        "Open_0": 35.791,
        "Open_1": 41.667,
        "Open_2": 35.832,
        "Volume_0": 58.231,
        "Volume_1": 64.025,
        "Volume_2": 45.113,
        "daily_return_0": 35.758,
        "daily_return_1": 23.097,
        "daily_return_2": 35.752,
        "daily_return_zscore_0": 23.036,
        "daily_return_zscore_1": 43.125,
        "daily_return_zscore_2": 23.4,
        "excess_return_0": 23.626,
        "excess_return_1": 23.52,
        "excess_return_2": 23.736,
        "high_low_range_0": 23.037,
        "high_low_range_1": 42.319,
        "high_low_range_2": 35.832,
        "log_return_0": 42.169,
        "log_return_1": 23.526,
        "log_return_2": 35.73,
        "log_return_zscore_0": 35.574,
        "log_return_zscore_1": 23.342,
        "log_return_zscore_2": 23.684,
        "log_volume_0": 43.691,
        "log_volume_1": 23.798,
        "log_volume_2": 35.636,
        "relative_volume_0": 23.365,
        "relative_volume_1": 35.663,
        "relative_volume_2": 23.337,
        "relative_volume_zscore_0": 23.781,
        "relative_volume_zscore_1": 23.026,
        "relative_volume_zscore_2": 42.275,
        "volume_change_0": 23.509,
        "volume_change_1": 44.303,
        "volume_change_2": 23.539,
        "volume_change_zscore_0": 23.569,
        "volume_change_zscore_1": 42.571,
        "volume_change_zscore_2": 23.728
      }
    },
    {
      "anomaly_index": 496,
      "feature_importances": {
        "Close_1": 23.008,
        "Close_2": 23.508,
        "High_0": 23.165,
        "High_1": 42.226,
        "High_2": 42.389,
        "Low_0": 42.093,
        "Low_1": 35.488,
        "Low_2": 23.436,
        "Open_0": 41.425,
        "Open_1": 23.497,
        "Open_2": 23.363,
        "Volume_0": 53.392,
        "Volume_1": 44.079,
        "Volume_2": 47.24,
        "daily_return_0": 23.084,
        "daily_return_1": 23.009,
        "daily_return_2": 35.373,
        "daily_return_zscore_0": 42.821,
        "daily_return_zscore_1": 23.302,
        "daily_return_zscore_2": 23.558,
        "excess_return_0": 23.541,
        "excess_return_1": 23.246,
        "excess_return_2": 35.534,
        "high_low_range_0": 23.136,
        "high_low_range_1": 35.333,
        "high_low_range_2": 23.404,
        "log_return_0": 42.025,
        "log_return_1": 35.638,
        "log_return_2": 35.519,
        "log_return_zscore_0": 23.453,
        "log_return_zscore_1": 23.345,
        "log_return_zscore_2": 35.492,
        "log_volume_0": 22.934,
        "log_volume_1": 35.694,
        "log_volume_2": 42.243,
        "relative_volume_0": 35.786,
        "relative_volume_1": 23.262,
        "relative_volume_2": 23.074,
        "relative_volume_zscore_0": 23.41,
        "relative_volume_zscore_1": 35.571,
        "relative_volume_zscore_2": 23.18,
        "volume_change_0": 23.429,
        "volume_change_1": 35.751,
        "volume_change_2": 23.21,
        "volume_change_zscore_0": 42.926,
        "volume_change_zscore_1": 23.342,
        "volume_change_zscore_2": 35.564
      }
    }
  ]
}